Metadata-Version: 1.1
Name: aiosasl
Version: 0.4.1
Summary: Pure-python, protocol agnostic SASL library for asyncio
Home-page: https://github.com/horazont/aiosasl
Author: Jonas Wielicki
Author-email: jonas@wielicki.name
License: GPL
Keywords: asyncio sasl library
Platform: UNKNOWN
Classifier: Development Status :: 4 - Beta
Classifier: Intended Audience :: Developers
Classifier: Programming Language :: Python :: 3 :: Only
Classifier: Programming Language :: Python :: 3.4
Classifier: Programming Language :: Python :: 3.5
Classifier: Programming Language :: Python :: 3.6
Classifier: Programming Language :: Python :: 3.7
Classifier: Programming Language :: Python :: 3.8
Classifier: License :: OSI Approved :: GNU Lesser General Public License v3 or later (LGPLv3+)
